{"__symbolic":"module","version":4,"metadata":{"SideMenuOptions":{"__symbolic":"interface"},"SideMenuHeader":{"__symbolic":"interface"},"SideMenuProfile":{"__symbolic":"interface"},"SideMenu":{"__symbolic":"interface"},"SideMenuItem":{"__symbolic":"interface"},"SideMenuComponent":{"__symbolic":"class","decorators":[{"__symbolic":"call","expression":{"__symbolic":"reference","module":"@angular/core","name":"Component","line":30,"character":1},"arguments":[{"selector":"ion-side-menu","template":"<div class=\"side-menu-container\">\n  <div *ngIf=\"options.header\" class=\"side-menu-header\"\n    [ngStyle]=\"options.header.background && {'background-image': 'url(' +\n    options.header.background + ')'}\" (click)=\"options.header.onClick &&\n    options.header.onClick()\">\n    <div *ngIf=\"options.header.profile\" class=\"profile\">\n      <div class=\"picture\">\n        <img [src]=\"options.header.profile.picture\">\n      </div>\n      <h2 class=\"name\">{{ options.header.profile.name }}</h2>\n      <p *ngIf=\"options.header.profile.email\" class=\"email\">{{\n        options.header.profile.email }}</p>\n    </div>\n  </div>\n  <ion-list lines=\"none\" no-padding>\n    <div *ngFor=\"let menu of options.menus\">\n      <ion-list-header *ngIf=\"menu.header\">{{ menu.header }}</ion-list-header>\n      <ion-menu-toggle auto-hide=\"false\" *ngFor=\"let item of menu.items\">\n        <ion-item [routerLink]=\"item.path && item.path\"\n          [routerLinkActive]=\"item.path && 'active'\"\n          [routerDirection]=\"item.path && 'root'\" (click)=\"item.onClick &&\n          item.onClick()\">\n          <ion-icon *ngIf=\"item.icon\" slot=\"start\" [name]=\"item.icon\"></ion-icon>\n          <ion-label>{{ item.title }}</ion-label>\n          <ion-badge *ngIf=\"item.badge\" slot=\"end\" [color]=\"item.badgeColor &&\n            item.badgeColor\">{{ item.badge }}</ion-badge>\n        </ion-item>\n      </ion-menu-toggle>\n      <hr *ngIf=\"menu.isDivider\" class=\"divider\">\n    </div>\n  </ion-list>\n</div>\n","styles":[".side-menu-container .side-menu-header{background-repeat:no-repeat;background-position:center;background-size:cover;height:160px;margin-bottom:8px;border-bottom:1px solid rgba(0,0,0,.13);padding:16px}.side-menu-container .side-menu-header .profile .picture{height:64px;width:64px}.side-menu-container .side-menu-header .profile .picture img{border-radius:50%}.side-menu-container .side-menu-header .profile .email,.side-menu-container .side-menu-header .profile .name{margin:0;font-size:14px;line-height:24px;color:#fff}.side-menu-container .side-menu-header .profile .name{margin-top:16px;font-weight:500}.side-menu-container .side-menu-header .profile .email{font-weight:400}.side-menu-container ion-list-header{margin-top:-8px}.side-menu-container .active{--background:var(--border-color)}.side-menu-container .active ion-icon,.side-menu-container .active ion-label{color:var(--ion-color-primary)}.side-menu-container .divider{border-bottom:1px solid rgba(0,0,0,.13)}"]}]}],"members":{"options":[{"__symbolic":"property","decorators":[{"__symbolic":"call","expression":{"__symbolic":"reference","module":"@angular/core","name":"Input","line":36,"character":3}}]}],"__ctor__":[{"__symbolic":"constructor"}]}},"IonicSideMenuModule":{"__symbolic":"class","decorators":[{"__symbolic":"call","expression":{"__symbolic":"reference","module":"@angular/core","name":"NgModule","line":7,"character":1},"arguments":[{"declarations":[{"__symbolic":"reference","name":"SideMenuComponent"}],"imports":[{"__symbolic":"reference","module":"@angular/common","name":"CommonModule","line":9,"character":12},{"__symbolic":"reference","module":"@ionic/angular","name":"IonicModule","line":9,"character":26},{"__symbolic":"reference","module":"@angular/router","name":"RouterModule","line":9,"character":39}],"exports":[{"__symbolic":"reference","name":"SideMenuComponent"}]}]}],"members":{}}},"origins":{"SideMenuOptions":"./lib/components/side-menu/side-menu.component","SideMenuHeader":"./lib/components/side-menu/side-menu.component","SideMenuProfile":"./lib/components/side-menu/side-menu.component","SideMenu":"./lib/components/side-menu/side-menu.component","SideMenuItem":"./lib/components/side-menu/side-menu.component","SideMenuComponent":"./lib/components/side-menu/side-menu.component","IonicSideMenuModule":"./lib/ionic-side-menu.module"},"importAs":"ionic-side-menu"}